parsers/__init__.py
parsers/base.py
parsers/tornado_parser.py
tests/__init__.py
tests/test_compiler.py
tests/test_manifest.py
tests/test_settings.py
tests/test_shunt.py
tests/test_tornado_templates.py
tornadoutils/RequestHandler.py
tornadoutils/__init__.py
tornadoutils/helpers.py
tornadoutils/static.py
py_assetman-0.3.0rc0.dist-info/LICENSE
py_assetman-0.3.0rc0.dist-info/METADATA
py_assetman-0.3.0rc0.dist-info/WHEEL
py_assetman-0.3.0rc0.dist-info/top_level.txt
py_assetman-0.3.0rc0.dist-info/RECORD
