Metadata-Version: 2.1
Name: py-assetman
Version: 0.3.0rc0
Summary: assetman assetmanager
Author-email: Will McCutchen <wm@bit.ly>
Maintainer-email: Jehiah Czebotar <jehiah@gmail.com>, Josh Harshman <josh.harshman@bit.ly>
Classifier: Programming Language :: Python :: 3
Classifier: License :: OSI Approved :: Apache Software License
Classifier: Operating System :: OS Independent
Requires-Python: >=3.8
License-File: LICENSE
Requires-Dist: boto3 >=1.34.15
Requires-Dist: tornado >=6.3.3
